MacSAFER-1.2.dist-info/DESCRIPTION.rst
MacSAFER-1.2.dist-info/METADATA
MacSAFER-1.2.dist-info/RECORD
MacSAFER-1.2.dist-info/WHEEL
MacSAFER-1.2.dist-info/entry_points.txt
MacSAFER-1.2.dist-info/metadata.json
MacSAFER-1.2.dist-info/top_level.txt
macsafer/MacSAFER.py
macsafer/__init__.py
macsafer/command_line.py
runnable/MacSAFER.py
runnable/__init__.py
runnable/command_line.py
