Metadata-Version: 2.0
Name: MacSAFER
Version: 1.2
Summary: Delete malicious plugins from korean e-commerce, government, online banking websites to make your mac clean.
Home-page: https://github.com/thy2134/MacSAFER
Author: Kyujin Cho
Author-email: thy2134@gmail.com
License: GPLv3
Platform: UNKNOWN
Classifier: Development Status :: 4 - Beta
Classifier: Intended Audience :: End Users/Desktop
Classifier: Topic :: Utilities
Classifier: License :: OSI Approved :: GNU General Public License v3 or later (GPLv3+)
Classifier: Programming Language :: Python :: 3.6
Classifier: Environment :: MacOS X
Classifier: Environment :: Console
Requires-Python: >=3
Requires-Dist: requests
